{
	"ImportPath": "github.com/alxeg/flibooks",
	"GoVersion": "go1.8",
	"GodepVersion": "v79",
	"Deps": [
		{
			"ImportPath": "github.com/emicklei/go-restful",
			"Comment": "2.2.0-4-gff4f55a",
			"Rev": "ff4f55a206334ef123e4f79bbf348980da81ca46"
		},
		{
			"ImportPath": "github.com/emicklei/go-restful/log",
			"Comment": "2.2.0-4-gff4f55a",
			"Rev": "ff4f55a206334ef123e4f79bbf348980da81ca46"
		},
		{
			"ImportPath": "github.com/go-sql-driver/mysql",
			"Comment": "v1.3-21-ge3f0fdc",
			"Rev": "e3f0fdcf52770a162d5a4540ddb8d9957ff456d1"
		},
		{
			"ImportPath": "github.com/jinzhu/gorm",
			"Comment": "v1.0-156-g9acaa33",
			"Rev": "9acaa33324bbcc78239a1c913d4f1292c12177b9"
		},
		{
			"ImportPath": "github.com/jinzhu/inflection",
			"Rev": "1c35d901db3da928c72a72d8458480cc9ade058f"
		},
		{
			"ImportPath": "github.com/mattn/go-sqlite3",
			"Comment": "v1.2.0-82-g83772a7",
			"Rev": "83772a7051f5e30d8e59746a9e43dfa706b72f3b"
		},
		{
			"ImportPath": "github.com/ogier/pflag",
			"Comment": "v0.0.1-7-g45c278a",
			"Rev": "45c278ab3607870051a2ea9040bb85fcb8557481"
		},
		{
			"ImportPath": "golang.org/x/net/context",
			"Rev": "3da985ce5951d99de868be4385f21ea6c2b22f24"
		}
	]
}
